JCOtimer/__init__.py
JCOtimer/timer.py
JCOtimer-7.0.dist-info/METADATA
JCOtimer-7.0.dist-info/RECORD
JCOtimer-7.0.dist-info/WHEEL
JCOtimer-7.0.dist-info/top_level.txt
