Metadata-Version: 2.1
Name: JCOtimer
Version: 7.0
Summary: JCOtimer is a Python utility/package for measuring function runtime.
Home-page: https://github.com/jancarloonce/JCOtimer
Author: Jan Carlo Once
Author-email: jancarloonce11@gmail.com
License: UNKNOWN
Platform: UNKNOWN
Classifier: Programming Language :: Python :: 3
Classifier: License :: OSI Approved :: MIT License
Classifier: Operating System :: OS Independent
